xia_actor_openai/__init__.py
xia_actor_openai/actor.cp310-win_amd64.pyd
xia_actor_openai/graphist.cp310-win_amd64.pyd
xia_actor_openai-0.1.4.dist-info/LICENSE.txt
xia_actor_openai-0.1.4.dist-info/METADATA
xia_actor_openai-0.1.4.dist-info/WHEEL
xia_actor_openai-0.1.4.dist-info/top_level.txt
xia_actor_openai-0.1.4.dist-info/RECORD
