Metadata-Version: 2.1
Name: xia-actor-openai
Version: 0.1.4
Summary: UNKNOWN
Home-page: https://develop.x-i-a.com/docs/xia-actor-openai/0.1.4/index.html
Author: X-I-A
Author-email: admin@x-i-a.com
License: UNKNOWN
Platform: UNKNOWN
Requires-Python: >=3.9
License-File: LICENSE.txt
Requires-Dist: openai
Requires-Dist: tiktoken
Requires-Dist: xia-actor
